sg_identity/__init__.py
sg_identity-0.2.0.dist-info/LICENSE
sg_identity-0.2.0.dist-info/METADATA
sg_identity-0.2.0.dist-info/WHEEL
sg_identity-0.2.0.dist-info/RECORD
