Metadata-Version: 2.1
Name: sg-identity
Version: 0.2.0
Summary: Hello PyPi
License: MIT
Author: Soof Golan
Author-email: pypi@soofgolan.com
Requires-Python: >=3.8,<4.0
Classifier: License :: OSI Approved :: MIT License
Classifier: Programming Language :: Python :: 3
Classifier: Programming Language :: Python :: 3.8
Classifier: Programming Language :: Python :: 3.9
Classifier: Programming Language :: Python :: 3.10
Classifier: Programming Language :: Python :: 3.11
Requires-Dist: typing-extensions (>=4.5.0,<5.0.0)
